{
  "topics": {
    "1": {
      "id": "1",
      "name_zh": "代码生成",
      "name_en": "Code Generation",
      "aliases": [],
      "status": "pending",
      "created_at": "2023-07-21T10:00:00.000Z"
    },
    "2": {
      "id": "2",
      "name_zh": "迁移学习",
      "name_en": "Transfer Learning",
      "aliases": [],
      "status": "pending",
      "created_at": "2025-08-05T18:52:43.106394"
    },
    "3": {
      "id": "3",
      "name_zh": "并行计算",
      "name_en": "Parallel Computing",
      "aliases": [],
      "status": "pending",
      "created_at": "2025-08-05T18:52:48.430053"
    },
    "4": {
      "id": "4",
      "name_zh": "图论",
      "name_en": "Graph Theory",
      "aliases": [
        "最短路径",
        "Shortest Paths"
      ],
      "status": "pending",
      "created_at": "2025-08-05T18:52:48.430267"
    },
    "5": {
      "id": "5",
      "name_zh": "硬件加速",
      "name_en": "Hardware Acceleration",
      "aliases": [
        "Compute-in-Memory",
        "矩阵乘法优化",
        "Autotuning",
        "自动调优",
        "Matrix Multiplication Optimization",
        "内存计算"
      ],
      "status": "pending",
      "created_at": "2025-08-05T18:54:05.978829"
    },
    "6": {
      "id": "6",
      "name_zh": "高斯Copula",
      "name_en": "Gaussian Copula",
      "aliases": [],
      "status": "pending",
      "created_at": "2025-08-05T19:25:32.804842"
    },
    "7": {
      "id": "7",
      "name_zh": "自动调优",
      "name_en": "Autotuning",
      "aliases": [],
      "status": "pending",
      "created_at": "2025-08-05T19:25:32.805081"
    },
    "8": {
      "id": "8",
      "name_zh": "强化学习",
      "name_en": "Reinforcement Learning",
      "aliases": [],
      "status": "pending",
      "created_at": "2025-08-05T19:25:50.783501"
    },
    "9": {
      "id": "9",
      "name_zh": "反事实推理",
      "name_en": "Counterfactual Reasoning",
      "aliases": [],
      "status": "pending",
      "created_at": "2025-08-05T19:25:50.783573"
    },
    "10": {
      "id": "10",
      "name_zh": "优化算法",
      "name_en": "Optimization Algorithms",
      "aliases": [],
      "status": "pending",
      "created_at": "2025-08-05T19:25:50.783621"
    },
    "11": {
      "id": "11",
      "name_zh": "博弈论",
      "name_en": "Game Theory",
      "aliases": [],
      "status": "pending",
      "created_at": "2025-08-05T19:25:50.783662"
    },
    "12": {
      "id": "12",
      "name_zh": "自动调优",
      "name_en": "Auto-tuning",
      "aliases": [],
      "status": "pending",
      "created_at": "2025-08-05T19:26:24.725209"
    },
    "13": {
      "id": "13",
      "name_zh": "多模态建模",
      "name_en": "Multi-modal Modeling",
      "aliases": [],
      "status": "pending",
      "created_at": "2025-08-05T19:26:24.725423"
    },
    "14": {
      "id": "14",
      "name_zh": "功耗管理",
      "name_en": "Power Management",
      "aliases": [],
      "status": "pending",
      "created_at": "2025-08-05T19:26:45.370090"
    },
    "15": {
      "id": "15",
      "name_zh": "数据中心优化",
      "name_en": "Datacenter Optimization",
      "aliases": [],
      "status": "pending",
      "created_at": "2025-08-05T19:26:45.370170"
    }
  },
  "version": "1.0.0",
  "last_updated": "2025-08-27T16:29:10.328377",
  "description": "存储阶段一询问大模型生成的主题词（待处理的主题词）"
}